bidcell-1.0.3.dist-info/METADATA
bidcell-1.0.3.dist-info/WHEEL
bidcell-1.0.3.dist-info/licenses/LICENSE
bidcell/BIDCellModel.py
bidcell/__init__.py
bidcell/config.py
bidcell/example_params/cosmx.yaml
bidcell/example_params/merscope.yaml
bidcell/example_params/small_example.yaml
bidcell/example_params/stereoseq.yaml
bidcell/example_params/xenium.yaml
bidcell/model/dataio/dataset_input.py
bidcell/model/model/intialisation.py
bidcell/model/model/layers.py
bidcell/model/model/losses.py
bidcell/model/model/model.py
bidcell/model/postprocess_predictions.py
bidcell/model/predict.py
bidcell/model/train.py
bidcell/model/utils/utils.py
bidcell/processing/cell_gene_matrix.py
bidcell/processing/nuclei_segmentation.py
bidcell/processing/nuclei_stitch_fov.py
bidcell/processing/preannotate.py
bidcell/processing/transcript_patches.py
bidcell/processing/transcripts.py
bidcell/processing/utils.py
data/dataset_xenium_breast1_small/morphology_mip_small.tif
data/dataset_xenium_breast1_small/transcripts_small.csv
data/example_mousebrain_genes.txt
data/sc_references/sc_breast.csv
data/sc_references/sc_breast_markers_neg.csv
data/sc_references/sc_breast_markers_pos.csv
bidcell-1.0.3.dist-info/RECORD
