Metadata-Version: 2.1
Name: bidcell
Version: 1.0.3
Summary: Biologically-informed deep learning for cell segmentation of subcelluar spatial transcriptomics data.
Author-Email: Helen Fu <xiaohang.fu@sydney.edu.au>
License: MIT
Requires-Python: <3.13,>=3.9
Requires-Dist: pandas>=2.1.0
Requires-Dist: numpy>=1.24.4
Requires-Dist: tifffile>=2023.8.30
Requires-Dist: imgaug>=0.4.0
Requires-Dist: h5py>=3.9.0
Requires-Dist: scipy>=1.11.2
Requires-Dist: matplotlib>=3.7.2
Requires-Dist: natsort>=8.4.0
Requires-Dist: cellpose>=2.2.3
Requires-Dist: scikit-image>=0.21.0
Requires-Dist: segmentation-models-pytorch>=0.3.3
Requires-Dist: opencv-python>=4.8.0.76
Requires-Dist: pillow>=10.0.0
Requires-Dist: pyyaml>=6.0.1
Requires-Dist: pydantic>=2.3.0
Requires-Dist: tqdm>=4.66.1
